mist_remote/__init__.py
mist_remote/__main__.py
mist_remote/remote.py
mist_remote-1.0.0.dist-info/LICENSE
mist_remote-1.0.0.dist-info/METADATA
mist_remote-1.0.0.dist-info/WHEEL
mist_remote-1.0.0.dist-info/entry_points.txt
mist_remote-1.0.0.dist-info/top_level.txt
mist_remote-1.0.0.dist-info/zip-safe
mist_remote-1.0.0.dist-info/RECORD
