Metadata-Version: 2.1
Name: mist-remote
Version: 1.0.0
Summary: Execute MIST playbooks in remote MIST server
Home-page: https://github.com/cr0hn/mist-remote
Author: UNKNOWN
Author-email: UNKNOWN
License: License :: OSI Approved :: BSD License
Platform: UNKNOWN
Classifier: Programming Language :: Python :: 3.6
Classifier: Programming Language :: Python :: 3.7
Classifier: Programming Language :: Python :: 3.8
Classifier: Programming Language :: Python :: 3.9
